static_file_service/__init__.py
static_file_service/common_pb2.py
static_file_service/common_pb2_grpc.py
static_file_service/grpc_client.py
static_file_service/models.py
static_file_service/staticFileService_pb2.py
static_file_service/staticFileService_pb2_grpc.py
longleding_static_file_service_sdk-0.2.8.dist-info/LICENSE
longleding_static_file_service_sdk-0.2.8.dist-info/METADATA
longleding_static_file_service_sdk-0.2.8.dist-info/WHEEL
longleding_static_file_service_sdk-0.2.8.dist-info/top_level.txt
longleding_static_file_service_sdk-0.2.8.dist-info/RECORD
