Metadata-Version: 2.1
Name: longleding-static-file-service-sdk
Version: 0.2.8
Summary: Longleding Static File Service SDK
Home-page: https://git.emhub.top/em/static-file-service
Author: Shi Ran
Author-email: ran.shi@longleding.com
License: UNKNOWN
Platform: UNKNOWN
Classifier: Programming Language :: Python :: 3
Classifier: Topic :: System :: Logging
Requires-Python: >=3.6
